TensorPlay/__init__.py
TensorPlay/core.py
TensorPlay/data.py
TensorPlay/func.py
TensorPlay/initializer.py
TensorPlay/layer.py
TensorPlay/module.py
TensorPlay/operator.py
TensorPlay/optimizer.py
TensorPlay/scheduler.py
TensorPlay/utils.py
tensorplay-0.1.2.dist-info/licenses/LICENSE
tensorplay-0.1.2.dist-info/METADATA
tensorplay-0.1.2.dist-info/WHEEL
tensorplay-0.1.2.dist-info/top_level.txt
tensorplay-0.1.2.dist-info/RECORD
